species/__init__.py
species/_version.py
species/core/__init__.py
species/core/box.py
species/core/constants.py
species/core/species_init.py
species/data/__init__.py
species/data/database.py
species/data/companion_data/__init__.py
species/data/companion_data/companion_data.json
species/data/companion_data/companion_spectra.json
species/data/companion_data/companion_spectra.py
species/data/filter_data/__init__.py
species/data/filter_data/filter_data.py
species/data/isochrone_data/__init__.py
species/data/isochrone_data/add_isochrone.py
species/data/isochrone_data/iso_ames.py
species/data/isochrone_data/iso_atmo.py
species/data/isochrone_data/iso_baraffe2015.py
species/data/isochrone_data/iso_btsettl.py
species/data/isochrone_data/iso_chabrier2023.py
species/data/isochrone_data/iso_linder2019.py
species/data/isochrone_data/iso_manual.py
species/data/isochrone_data/iso_marleau2014.py
species/data/isochrone_data/iso_nextgen.py
species/data/isochrone_data/iso_parsec.py
species/data/isochrone_data/iso_saumon2008.py
species/data/isochrone_data/iso_sonora_bobcat.py
species/data/isochrone_data/iso_sonora_diamondback.py
species/data/isochrone_data/iso_spiegel2012.py
species/data/misc_data/__init__.py
species/data/misc_data/accretion_data.py
species/data/misc_data/dust_data.py
species/data/model_data/__init__.py
species/data/model_data/custom_model.py
species/data/model_data/model_data.json
species/data/model_data/model_spectra.py
species/data/phot_data/__init__.py
species/data/phot_data/phot_jwst_ydwarfs.py
species/data/phot_data/phot_leggett.py
species/data/phot_data/phot_vlm_plx.py
species/data/spec_data/__init__.py
species/data/spec_data/add_spec_data.py
species/data/spec_data/spec_allers2013.py
species/data/spec_data/spec_bonnefoy2014.py
species/data/spec_data/spec_irtf.py
species/data/spec_data/spec_kesseli2017.py
species/data/spec_data/spec_spex.py
species/data/spec_data/spec_vega.py
species/fit/__init__.py
species/fit/compare_spectra.py
species/fit/emission_line.py
species-0.10.4.dist-info/licenses/LICENSE
species-0.10.4.dist-info/METADATA
species-0.10.4.dist-info/WHEEL
species-0.10.4.dist-info/top_level.txt
species-0.10.4.dist-info/RECORD
