Metadata-Version: 2.4
Name: species
Version: 0.10.4
Summary: Toolkit for atmospheric characterization of directly imaged exoplanets
Author-email: Tomas Stolker <stolker@strw.leidenuniv.nl>
License-Expression: MIT
Project-URL: Documentation, https://species.readthedocs.io
Project-URL: Repository, https://github.com/tomasstolker/species
Project-URL: Issues, https://github.com/tomasstolker/species/issues
Classifier: Programming Language :: Python :: 3.11
Classifier: Programming Language :: Python :: 3.12
Classifier: Programming Language :: Python :: 3.13
Classifier: Intended Audience :: Science/Research
Classifier: Topic :: Scientific/Engineering :: Astronomy
Requires-Python: <3.14,>=3.11
License-File: LICENSE
Requires-Dist: astropy
Requires-Dist: beartype
Requires-Dist: dust-extinction
Requires-Dist: h5py
Requires-Dist: matplotlib
Requires-Dist: numba
Requires-Dist: numpy
Requires-Dist: pooch
Requires-Dist: scipy
Requires-Dist: spectres
Requires-Dist: tqdm
Provides-Extra: full
Requires-Dist: astrodbkit2; extra == "full"
Requires-Dist: astroquery; extra == "full"
Requires-Dist: dynesty; extra == "full"
Requires-Dist: emcee; extra == "full"
Requires-Dist: molmass; extra == "full"
Requires-Dist: pandas; extra == "full"
Requires-Dist: PyMieScatt; extra == "full"
Requires-Dist: pymultinest; extra == "full"
Requires-Dist: requests; extra == "full"
Requires-Dist: schwimmbad; extra == "full"
Requires-Dist: shapely; extra == "full"
Requires-Dist: specutils; extra == "full"
Requires-Dist: SQLAlchemy; extra == "full"
Requires-Dist: ultranest; extra == "full"
Requires-Dist: xlrd; extra == "full"
Provides-Extra: docs
Requires-Dist: cython; extra == "docs"
Requires-Dist: jupyter; extra == "docs"
Requires-Dist: nbsphinx; extra == "docs"
Requires-Dist: pandoc; extra == "docs"
Requires-Dist: sphinx; extra == "docs"
Requires-Dist: sphinx-automodapi; extra == "docs"
Requires-Dist: sphinxawesome-theme; extra == "docs"
Provides-Extra: test
Requires-Dist: black; extra == "test"
Requires-Dist: flake8; extra == "test"
Requires-Dist: pycodestyle; extra == "test"
Requires-Dist: pylint; extra == "test"
Requires-Dist: pytest; extra == "test"
Requires-Dist: pytest-cov; extra == "test"
Dynamic: license-file
